odoo/addons/hr_timesheet_day_week/README.rst
odoo/addons/hr_timesheet_day_week/__init__.py
odoo/addons/hr_timesheet_day_week/__manifest__.py
odoo/addons/hr_timesheet_day_week/hooks.py
odoo/addons/hr_timesheet_day_week/i18n/es.po
odoo/addons/hr_timesheet_day_week/i18n/hr_timesheet_day_week.pot
odoo/addons/hr_timesheet_day_week/i18n/it.po
odoo/addons/hr_timesheet_day_week/models/__init__.py
odoo/addons/hr_timesheet_day_week/models/account_analytic_line.py
odoo/addons/hr_timesheet_day_week/readme/CONTRIBUTORS.md
odoo/addons/hr_timesheet_day_week/readme/DESCRIPTION.md
odoo/addons/hr_timesheet_day_week/readme/ROADMAP.md
odoo/addons/hr_timesheet_day_week/readme/USAGE.md
odoo/addons/hr_timesheet_day_week/report/__init__.py
odoo/addons/hr_timesheet_day_week/report/timesheets_analysis_report.py
odoo/addons/hr_timesheet_day_week/report/timesheets_analysis_report.xml
odoo/addons/hr_timesheet_day_week/static/description/icon.png
odoo/addons/hr_timesheet_day_week/static/description/index.html
odoo/addons/hr_timesheet_day_week/static/img/01_search.png
odoo/addons/hr_timesheet_day_week/static/img/02_groupby.png
odoo/addons/hr_timesheet_day_week/static/img/03_list.png
odoo/addons/hr_timesheet_day_week/static/img/04_filter.png
odoo/addons/hr_timesheet_day_week/tests/__init__.py
odoo/addons/hr_timesheet_day_week/tests/test_hr_timesheet_day_week.py
odoo/addons/hr_timesheet_day_week/views/hr_timesheet_view.xml
odoo_addon_hr_timesheet_day_week-18.0.1.0.0.4.dist-info/METADATA
odoo_addon_hr_timesheet_day_week-18.0.1.0.0.4.dist-info/WHEEL
odoo_addon_hr_timesheet_day_week-18.0.1.0.0.4.dist-info/top_level.txt
odoo_addon_hr_timesheet_day_week-18.0.1.0.0.4.dist-info/RECORD
