Metadata-Version: 2.1
Name: odoo-addon-hr_timesheet_day_week
Version: 18.0.1.0.0.4
Requires-Python: >=3.10
Requires-Dist: odoo==18.0.*
Summary: Timesheets - Day of Week
Home-page: https://github.com/OCA/timesheet
License: AGPL-3
Author: Solvos, Odoo Community Association (OCA)
Author-email: support@odoo-community.org
Classifier: Programming Language :: Python
Classifier: Framework :: Odoo
Classifier: Framework :: Odoo :: 18.0
Classifier: License :: OSI Approved :: GNU Affero General Public License v3
